pymmt/__init__.py
pymmt/pymmt.py
pymmt/instruments/__init__.py
pymmt/instruments/binospec.py
pymmt/instruments/mmirs.py
PyMMT-1.0.0.dist-info/METADATA
PyMMT-1.0.0.dist-info/WHEEL
PyMMT-1.0.0.dist-info/top_level.txt
PyMMT-1.0.0.dist-info/RECORD
