Metadata-Version: 2.1
Name: PyMMT
Version: 1.0.0
Summary: A python API wrapper for the MMT Observatory
Author-email: Samuel Wyatt <swyatt@arizona.edu>, Manisha Shrestha <mshrestha1@arizona.edu>, Griffin Hosseinzadeh <griffin0@arizona.edu>
Project-URL: Homepage, https://github.com/SAGUARO-MMA/PyMMT
Project-URL: Bug Tracker, https://github.com/SAGUARO-MMA/PyMMT/issues
Classifier: Programming Language :: Python :: 3
Classifier: License :: OSI Approved :: MIT License
Classifier: Operating System :: OS Independent
Requires-Python: >=3.10
Requires-Dist: requests
Requires-Dist: setuptools-scm
Requires-Dist: ipykernel
